cgem/__init__.py
cgem/models.py
cgem/terms.py
cgem-0.1.0.dist-info/LICENSE
cgem-0.1.0.dist-info/METADATA
cgem-0.1.0.dist-info/WHEEL
cgem-0.1.0.dist-info/top_level.txt
cgem-0.1.0.dist-info/RECORD
